gdax/__init__.py
gdax/endpoints.py
gdax/exceptions.py
gdax/public_client.py
gdax/validators.py
gdax/version.py
python_gdaxapi-0.0.2.dist-info/DESCRIPTION.rst
python_gdaxapi-0.0.2.dist-info/METADATA
python_gdaxapi-0.0.2.dist-info/RECORD
python_gdaxapi-0.0.2.dist-info/WHEEL
python_gdaxapi-0.0.2.dist-info/metadata.json
python_gdaxapi-0.0.2.dist-info/top_level.txt
