Metadata-Version: 2.0
Name: python-gdaxapi
Version: 0.0.2
Summary: GDAX API wrapper for Python
Home-page: https://github.com/jtstio/python-gdaxapi
Author: Jay Hale
Author-email: jay@jtst.io
License: MIT
Keywords: gdax,gdax-api,bitcoin,ethereum,litecoin,BTC,ETH,LTC,client,api,wrapper,currency,trading,trading-api,coinbase
Platform: UNKNOWN
Classifier: Development Status :: 5 - Production/Stable
Classifier: Intended Audience :: Developers
Classifier: Intended Audience :: Financial and Insurance Industry
Classifier: Intended Audience :: Information Technology
Classifier: Topic :: Software Development :: Libraries :: Python Modules
Classifier: License :: OSI Approved :: MIT License
Classifier: Programming Language :: Python :: 2
Classifier: Programming Language :: Python :: 2.6
Classifier: Programming Language :: Python :: 2.7
Classifier: Programming Language :: Python :: 3
Classifier: Programming Language :: Python :: 3.3
Classifier: Programming Language :: Python :: 3.4
Classifier: Programming Language :: Python :: 3.5
Classifier: Topic :: Software Development :: Libraries :: Python Modules
Requires-Dist: requests (<3,>=2.18)
